aind_large_scale_prediction/__init__.py
aind_large_scale_prediction/_shared/__init__.py
aind_large_scale_prediction/_shared/types.py
aind_large_scale_prediction/generator/__init__.py
aind_large_scale_prediction/generator/dataloader.py
aind_large_scale_prediction/generator/dataset.py
aind_large_scale_prediction/generator/utils.py
aind_large_scale_prediction/generator/zarr_slice_generator.py
aind_large_scale_prediction/io/__init__.py
aind_large_scale_prediction/io/_io.py
aind_large_scale_prediction/io/utils.py
aind_large_scale_prediction-1.0.0.dist-info/LICENSE
aind_large_scale_prediction-1.0.0.dist-info/METADATA
aind_large_scale_prediction-1.0.0.dist-info/WHEEL
aind_large_scale_prediction-1.0.0.dist-info/top_level.txt
aind_large_scale_prediction-1.0.0.dist-info/RECORD
