Metadata-Version: 2.1
Name: aind-large-scale-prediction
Version: 1.0.0
Summary: Generated from aind-library-template
Author: Allen Institute for Neural Dynamics
License: MIT
Classifier: Programming Language :: Python :: 3
Requires-Python: >=3.9
License-File: LICENSE
Requires-Dist: ome-zarr ==0.8.3
Requires-Dist: numpy ==1.26.4
Requires-Dist: zarr ==2.18.0
Requires-Dist: scikit-learn ==1.4.2
Requires-Dist: pims ==0.6.1
Requires-Dist: imagecodecs[all] ==2024.1.1
Requires-Dist: tifffile ==2024.5.10
Requires-Dist: dask[distributed] ==2024.4.1
Requires-Dist: dask-image ==2023.8.1
Requires-Dist: torch ==2.2.2
Provides-Extra: dev
Requires-Dist: black ; extra == 'dev'
Requires-Dist: coverage ; extra == 'dev'
Requires-Dist: flake8 ; extra == 'dev'
Requires-Dist: interrogate ; extra == 'dev'
Requires-Dist: isort ; extra == 'dev'
Requires-Dist: Sphinx ; extra == 'dev'
Requires-Dist: furo ; extra == 'dev'
